expmate/__init__.py
expmate/config.py
expmate/git.py
expmate/logger.py
expmate/monitor.py
expmate/parser.py
expmate/tracking.py
expmate/utils.py
expmate/cli/__init__.py
expmate/cli/compare.py
expmate/cli/main.py
expmate/cli/sweep.py
expmate/cli/visualize.py
expmate/torch/__init__.py
expmate/torch/checkpoint.py
expmate/torch/mp.py
expmate-0.1.1.dist-info/licenses/LICENSE
expmate-0.1.1.dist-info/METADATA
expmate-0.1.1.dist-info/WHEEL
expmate-0.1.1.dist-info/entry_points.txt
expmate-0.1.1.dist-info/top_level.txt
expmate-0.1.1.dist-info/RECORD
