Metadata-Version: 2.4
Name: expmate
Version: 0.1.1
Summary: ML Research Boilerplate — Config & Logging First
Author-email: Kunhee Kim <kunhee.kim@kaist.ac.kr>
License: MIT
Project-URL: Homepage, https://github.com/kunheek/expmate
Project-URL: Repository, https://github.com/kunheek/expmate
Project-URL: Documentation, https://github.com/kunheek/expmate#readme
Project-URL: Changelog, https://github.com/kunheek/expmate/blob/main/CHANGELOG.md
Project-URL: Issues, https://github.com/kunheek/expmate/issues
Keywords: machine-learning,deep-learning,experiment-tracking,pytorch,configuration,logging,reproducibility,research,cli
Classifier: Development Status :: 4 - Beta
Classifier: Intended Audience :: Developers
Classifier: Intended Audience :: Science/Research
Classifier: License :: OSI Approved :: MIT License
Classifier: Programming Language :: Python :: 3
Classifier: Programming Language :: Python :: 3.8
Classifier: Programming Language :: Python :: 3.9
Classifier: Programming Language :: Python :: 3.10
Classifier: Programming Language :: Python :: 3.11
Classifier: Programming Language :: Python :: 3.12
Classifier: Topic :: Scientific/Engineering :: Artificial Intelligence
Classifier: Topic :: Software Development :: Libraries :: Python Modules
Requires-Python: >=3.8
License-File: LICENSE
Requires-Dist: numpy>=1.21.0
Requires-Dist: matplotlib>=3.5.0
Requires-Dist: polars>=0.20.0
Requires-Dist: psutil>=5.9.0
Requires-Dist: pyyaml>=6.0
Provides-Extra: wandb
Requires-Dist: wandb>=0.15.0; extra == "wandb"
Provides-Extra: tensorboard
Requires-Dist: tensorboard>=2.13.0; extra == "tensorboard"
Provides-Extra: tracking
Requires-Dist: wandb>=0.15.0; extra == "tracking"
Requires-Dist: tensorboard>=2.13.0; extra == "tracking"
Provides-Extra: dev
Requires-Dist: pytest>=7.0.0; extra == "dev"
Requires-Dist: pytest-cov>=4.0.0; extra == "dev"
Requires-Dist: black>=23.0.0; extra == "dev"
Requires-Dist: ruff>=0.1.0; extra == "dev"
Requires-Dist: mypy>=1.0.0; extra == "dev"
Requires-Dist: pre-commit>=3.0.0; extra == "dev"
Dynamic: license-file
